wldhx/__init__.py
wldhx/yadisk_direct/__init__.py
wldhx/yadisk_direct/main.py
wldhx.yadisk_direct-0.0.6.dist-info/DESCRIPTION.rst
wldhx.yadisk_direct-0.0.6.dist-info/METADATA
wldhx.yadisk_direct-0.0.6.dist-info/RECORD
wldhx.yadisk_direct-0.0.6.dist-info/WHEEL
wldhx.yadisk_direct-0.0.6.dist-info/entry_points.txt
wldhx.yadisk_direct-0.0.6.dist-info/metadata.json
wldhx.yadisk_direct-0.0.6.dist-info/top_level.txt
wldhx.yadisk_direct-0.0.6.dist-info/zip-safe
