Metadata-Version: 2.0
Name: wldhx.yadisk-direct
Version: 0.0.6
Summary: Get real direct links usable with tools like curl or wget for files stored in Yandex.Disk
Home-page: https://gitlab.com/wldhx/yadisk-direct
Author: wldhx
Author-email: wldhx+pypi_python_org@wldhx.me
License: GPLv3
Keywords: Yandex.Disk
Platform: UNKNOWN
Classifier: License :: OSI Approved :: GNU General Public License v3 or later (GPLv3+)
Classifier: Programming Language :: Python :: 3
Classifier: Topic :: Utilities
Requires-Dist: requests
